pybetareg/__init__.py
pybetareg/api.py
pybetareg/main.py
pybetareg-1.0.0.dist-info/METADATA
pybetareg-1.0.0.dist-info/WHEEL
pybetareg-1.0.0.dist-info/top_level.txt
pybetareg-1.0.0.dist-info/RECORD
