Metadata-Version: 2.1
Name: pybetareg
Version: 1.0.0
Summary: Beta modal regression
Home-page: https://rh8liuqy.github.io/
Author: Qingyang Liu
Author-email: qingyang@email.sc.edu
License: MIT
Platform: UNKNOWN
Classifier: License :: OSI Approved :: MIT License
Classifier: Programming Language :: Python :: 3
Classifier: Programming Language :: Python :: 3.7
Requires-Dist: numpy
Requires-Dist: pandas
Requires-Dist: numdifftools
Requires-Dist: scipy
